puancore/__init__.py
puancore/comp/__init__.py
puancore/linalg/__init__.py
puancore/linalg/matrix/__init__.py
puancore/linalg/vmap/__init__.py
puancore/logic/__init__.py
puancore/logic/cnf/__init__.py
puancore/logic/crc/__init__.py
puancore/logic/sta/__init__.py
puancore/misc/__init__.py
puancore/uFuncs/__init__.py
puancore/uFuncs/npufunc.cpython-39-darwin.so
puancore-1.6.dist-info/LICENSE
puancore-1.6.dist-info/METADATA
puancore-1.6.dist-info/WHEEL
puancore-1.6.dist-info/top_level.txt
puancore-1.6.dist-info/RECORD
